ss_roster2csv/__init__.py
ss_roster2csv/__main__.py
ss_roster2csv/cli.py
ss_roster2csv/helper.py
ss_roster2csv/io_utils.py
ss_roster2csv/logging_config.py
ss_roster2csv/mytypes.py
ss_roster2csv/parser.py
tests/__init__.py
tests/test_cli.py
tests/test_data_integrity.py
tests/test_io_utils.py
tests/test_parser.py
ss_roster2csv-0.1.0.dist-info/METADATA
ss_roster2csv-0.1.0.dist-info/WHEEL
ss_roster2csv-0.1.0.dist-info/entry_points.txt
ss_roster2csv-0.1.0.dist-info/top_level.txt
ss_roster2csv-0.1.0.dist-info/RECORD
